mayalauncher.py
mayalauncher-0.2.0.dist-info/DESCRIPTION.rst
mayalauncher-0.2.0.dist-info/METADATA
mayalauncher-0.2.0.dist-info/RECORD
mayalauncher-0.2.0.dist-info/WHEEL
mayalauncher-0.2.0.dist-info/entry_points.txt
mayalauncher-0.2.0.dist-info/metadata.json
mayalauncher-0.2.0.dist-info/pbr.json
mayalauncher-0.2.0.dist-info/top_level.txt
