Metadata-Version: 2.0
Name: mayalauncher
Version: 0.2.0
Summary: Autodesk Maya application launcher.
Home-page: https://github.com/arubertoson/maya-launcher
Author: Marcus Albertsson
Author-email: marcus.arubertoson@gmail.com
License: MIT
Platform: UNKNOWN
Classifier: Development Status :: 3 - Alpha
Classifier: Programming Language :: Python :: 2
Classifier: Intended Audience :: End Users/Desktop
Classifier: Environment :: Console
Requires-Dist: argsparse; python_version=="2.6"
Requires-Dist: pathlib; python_version=="2.6"
Requires-Dist: shutilwhich; python_version=="2.6"
Requires-Dist: pathlib; python_version=="2.7"
Requires-Dist: shutilwhich; python_version=="2.7"
Requires-Dist: pathlib; python_version=="3.2"
Requires-Dist: shutilwhich; python_version=="3.2"
Requires-Dist: pathlib; python_version=="3.5"
Requires-Dist: shutilwhich; python_version=="3.5"
